charms/proxylib/__init__.py
charms/proxylib/errors.py
charms/proxylib/model.py
charms/proxylib/view.py
charms_proxylib-0.0.0.dist-info/licenses/LICENSE
charms_proxylib-0.0.0.dist-info/METADATA
charms_proxylib-0.0.0.dist-info/WHEEL
charms_proxylib-0.0.0.dist-info/top_level.txt
charms_proxylib-0.0.0.dist-info/zip-safe
charms_proxylib-0.0.0.dist-info/RECORD
