Metadata-Version: 2.4
Name: charms.proxylib
Version: 0.0.0
Summary: Charm library for juju-*-proxy model config
Author-email: Adam Dyess <adam.dyess@canonical.com>, Mateo Florido <mateo.florido@canonical.com>
License-Expression: Apache-2.0
Project-URL: Repository, https://github.com/canonical/charms.proxylib
Project-URL: BugTracker, https://github.com/canonical/charms.proxylib/issues
Keywords: juju,charming,operators,systemd,web-proxy,validation
Classifier: Programming Language :: Python
Classifier: Programming Language :: Python :: 3
Classifier: Programming Language :: Python :: 3.10
Classifier: Programming Language :: Python :: 3.11
Classifier: Programming Language :: Python :: 3.12
Requires-Python: >=3.10
License-File: LICENSE
Provides-Extra: lightkube
Requires-Dist: lightkube; extra == "lightkube"
Dynamic: license-file
